fuzzy.py
fuzzy_PaulUTC-0.2.4.dist-info/LICENSE.txt
fuzzy_PaulUTC-0.2.4.dist-info/METADATA
fuzzy_PaulUTC-0.2.4.dist-info/WHEEL
fuzzy_PaulUTC-0.2.4.dist-info/top_level.txt
fuzzy_PaulUTC-0.2.4.dist-info/RECORD
