Metadata-Version: 2.1
Name: fuzzy_PaulUTC
Version: 0.2.4
Summary: Package pour traiter les mathématiques du floue.
Home-page: https://github.com/Popolito2/fuzzy
Author: Paul Coulombel
Author-email: paul.coulombel@etu.utc.fr
Classifier: Programming Language :: Python :: 3
Classifier: License :: OSI Approved :: MIT License
Classifier: Operating System :: OS Independent
Requires-Python: >=3.8
License-File: LICENSE.txt
